quantum_jet.libs/libgfortran-91cc3cb1.so.3.0.0
quantum_jet.libs/libquadmath-96973f99.so.0.0.0
quantum_jet.libs/libopenblas-r0-f650aae0.3.3.so
quantum_jet-0.2.2.dist-info/LICENSE
quantum_jet-0.2.2.dist-info/top_level.txt
quantum_jet-0.2.2.dist-info/RECORD
quantum_jet-0.2.2.dist-info/WHEEL
quantum_jet-0.2.2.dist-info/METADATA
jet/__init__.py
jet/gate.py
jet/bindings.cpython-39-x86_64-linux-gnu.so
jet/interpreter.py
jet/state.py
jet/circuit.py
jet/factory.py
