Metadata-Version: 2.1
Name: quantum-jet
Version: 0.2.2
Summary: Jet is an open-source library for quantum circuit simulation using tensor network contractions
Home-page: https://github.com/XanaduAI/jet
Maintainer: Xanadu Inc.
Maintainer-email: software@xanadu.ai
License: Apache License 2.0
Platform: UNKNOWN
Classifier: Development Status :: 3 - Alpha
Classifier: Environment :: Console
Classifier: Intended Audience :: Science/Research
Classifier: License :: OSI Approved :: Apache Software License
Classifier: Natural Language :: English
Classifier: Operating System :: POSIX
Classifier: Operating System :: MacOS :: MacOS X
Classifier: Operating System :: POSIX :: Linux
Classifier: Programming Language :: Python
Classifier: Programming Language :: Python :: 3
Classifier: Programming Language :: Python :: 3.7
Classifier: Programming Language :: Python :: 3.8
Classifier: Programming Language :: Python :: 3.9
Classifier: Programming Language :: Python :: 3 :: Only
Classifier: Topic :: Scientific/Engineering :: Physics
Provides: jet
Provides: xir
License-File: LICENSE
Requires-Dist: numpy (<1.21.0)
Requires-Dist: quantum-xir
Requires-Dist: strawberryfields (>=0.18.0)
Requires-Dist: thewalrus (>=0.15.0)
